rsyncr/.corrupdetect
rsyncr/.flake8
rsyncr/__init__.py
rsyncr/__main__.py
rsyncr/distance.py
rsyncr/help.py
rsyncr/rsyncr.py
rsyncr-2025.1121.2115.dist-info/METADATA
rsyncr-2025.1121.2115.dist-info/WHEEL
rsyncr-2025.1121.2115.dist-info/entry_points.txt
rsyncr-2025.1121.2115.dist-info/licenses/LICENSE
rsyncr-2025.1121.2115.dist-info/RECORD
