Metadata-Version: 2.4
Name: rsyncr
Version: 2025.1121.2115
Summary: rsyncr - An enhanced rsync backup wrapper script
Project-URL: Homepage, http://github.com/ArneBachmann/rsyncr
Author-email: Arne Bachmann <ArneBachmann@users.noreply.github.com>
License-Expression: GPL-3.0-or-later
License-File: LICENSE
Keywords: UI,backup,feedback,interface,rsync,safety,wrapper
Classifier: Development Status :: 5 - Production/Stable
Classifier: Intended Audience :: Science/Research
Classifier: Intended Audience :: System Administrators
Classifier: License :: OSI Approved :: GNU General Public License v3 (GPLv3)
Classifier: Operating System :: OS Independent
Classifier: Programming Language :: Python
Classifier: Programming Language :: Python :: 3.11
Requires-Python: >=3.11
Requires-Dist: appdirs
Requires-Dist: beartype
Requires-Dist: brew-distance
Requires-Dist: chardet
Requires-Dist: edit-distance
Requires-Dist: stringdist
Requires-Dist: typing-extensions
Provides-Extra: dev
Requires-Dist: types-appdirs; extra == 'dev'
